{
  "appPageId" : "cb6edbe7-793b-4841-b251-b365ea50459b",
  "componentName" : "siteforce:sldsOneColLayout",
  "id" : "65681dfe-c982-4654-b622-cd1bdb21f455",
  "label" : "Flow",
  "regions" : [ {
    "id" : "0066fe7f-a261-4c95-a184-59a6df4385be",
    "regionName" : "header",
    "type" : "region"
  }, {
    "components" : [ {
      "componentAttributes" : {
        "flowArguments" : "",
        "flowLayout" : "oneColumn",
        "flowName" : "{!flowName}"
      },
      "componentName" : "forceCommunity:flowCommunity",
      "id" : "b4355a83-420b-4909-b153-bbfeaefa2963",
      "renderPriority" : "NEUTRAL",
      "renditionMap" : { },
      "type" : "component"
    } ],
    "id" : "72ad98b1-8844-423a-afb3-233eca8a243f",
    "regionName" : "content",
    "type" : "region"
  }, {
    "id" : "b1f1633e-972a-4ec2-80f7-5dc7854377a7",
    "regionName" : "footer",
    "type" : "region"
  } ],
  "themeLayoutType" : "Inner",
  "type" : "view",
  "viewType" : "flow"
}