{
  "appPageId" : "36fccdb8-95e1-4230-a3e9-9477b291927e",
  "componentName" : "siteforce:sldsOneColLayout",
  "id" : "26c19611-936a-403a-bbb6-b2bac4c9d759",
  "label" : "Login Error",
  "regions" : [ {
    "id" : "728cfb32-e8c8-488b-a643-b9d941d494a6",
    "regionName" : "header",
    "type" : "region"
  }, {
    "components" : [ {
      "componentAttributes" : {
        "richTextValue" : "<div style=\"text-align: center;\">Invalid Page</div>"
      },
      "componentName" : "forceCommunity:richTextInline",
      "id" : "88179f52-127f-48bd-a276-a5aecf9ba7aa",
      "renderPriority" : "NEUTRAL",
      "renditionMap" : { },
      "type" : "component"
    } ],
    "id" : "0cfe17b7-7d49-4581-98ba-475ed6dbf994",
    "regionName" : "content",
    "type" : "region"
  }, {
    "id" : "4de1dd90-c42f-4335-8dd8-6d3eb02b302f",
    "regionName" : "footer",
    "type" : "region"
  }, {
    "components" : [ {
      "componentAttributes" : {
        "customHeadTags" : "",
        "description" : "",
        "title" : "Login Error"
      },
      "componentName" : "forceCommunity:seoAssistant",
      "id" : "fde12a30-b715-4e0a-96c5-84bb8ea5058e",
      "renditionMap" : { },
      "type" : "component"
    } ],
    "id" : "a4ec09d7-d33f-48e1-bdad-f31af3fcbc1a",
    "regionName" : "sfdcHiddenRegion",
    "type" : "region"
  } ],
  "themeLayoutType" : "Login",
  "type" : "view",
  "viewType" : "login-error"
}